{
  "name": "item",
  "base": "PersistedModel",
  "idInjection": true,
  "options": {
    "validateUpsert": true
  },
  "properties": {
    "name": {
      "type": "string"
    },
    "description": {
      "type": "string"
    },
    "imageurl": {
      "type": "string"
    },
    "detailurl": {
      "type": "string"
    },
    "brandId": {
      "type": "string",
      "description": "Brand ID"
    },
    "keyword": {
      "type": "string"
    },
    "createdDate": {
      "type": "date"
    },
    "updatedDate": {
      "type": "date"
    },
    "orderId": {
      "type": "number"
    }
  },
  "validations": [],
  "relations": {
    "brand": {
      "type": "belongsTo",
      "model": "brand",
      "foreignKey": ""
    }
  },
  "acls": [],
  "methods": {}
}
